{
    "url": "https://api.github.com/repos/spack/spack/issues/13769",
    "repository_url": "https://api.github.com/repos/spack/spack",
    "labels_url": "https://api.github.com/repos/spack/spack/issues/13769/labels{/name}",
    "comments_url": "https://api.github.com/repos/spack/spack/issues/13769/comments",
    "events_url": "https://api.github.com/repos/spack/spack/issues/13769/events",
    "html_url": "https://github.com/spack/spack/pull/13769",
    "id": 524273919,
    "node_id": "MDExOlB1bGxSZXF1ZXN0MzQyMDc3MDk0",
    "number": 13769,
    "title": "add MAX_CPU_COUNT variant to HPX package",
    "user": {
        "login": "albestro",
        "id": 9337627,
        "node_id": "MDQ6VXNlcjkzMzc2Mjc=",
        "avatar_url": "https://avatars.githubusercontent.com/u/9337627?v=4",
        "gravatar_id": "",
        "url": "https://api.github.com/users/albestro",
        "html_url": "https://github.com/albestro",
        "followers_url": "https://api.github.com/users/albestro/followers",
        "following_url": "https://api.github.com/users/albestro/following{/other_user}",
        "gists_url": "https://api.github.com/users/albestro/gists{/gist_id}",
        "starred_url": "https://api.github.com/users/albestro/starred{/owner}{/repo}",
        "subscriptions_url": "https://api.github.com/users/albestro/subscriptions",
        "organizations_url": "https://api.github.com/users/albestro/orgs",
        "repos_url": "https://api.github.com/users/albestro/repos",
        "events_url": "https://api.github.com/users/albestro/events{/privacy}",
        "received_events_url": "https://api.github.com/users/albestro/received_events",
        "type": "User",
        "site_admin": false
    },
    "labels": [
        {
            "id": 729584669,
            "node_id": "MDU6TGFiZWw3Mjk1ODQ2Njk=",
            "url": "https://api.github.com/repos/spack/spack/labels/update-package",
            "name": "update-package",
            "color": "c68137",
            "default": false,
            "description": null
        },
        {
            "id": 493969518,
            "node_id": "MDU6TGFiZWw0OTM5Njk1MTg=",
            "url": "https://api.github.com/repos/spack/spack/labels/variants",
            "name": "variants",
            "color": "c2e0c6",
            "default": false,
            "description": null
        }
    ],
    "state": "closed",
    "locked": false,
    "assignee": null,
    "assignees": [],
    "milestone": null,
    "comments": 0,
    "created_at": "2019-11-18T10:28:38Z",
    "updated_at": "2019-11-20T08:18:35Z",
    "closed_at": "2019-11-19T19:49:33Z",
    "author_association": "CONTRIBUTOR",
    "active_lock_reason": null,
    "pull_request": {
        "url": "https://api.github.com/repos/spack/spack/pulls/13769",
        "html_url": "https://github.com/spack/spack/pull/13769",
        "diff_url": "https://github.com/spack/spack/pull/13769.diff",
        "patch_url": "https://github.com/spack/spack/pull/13769.patch"
    },
    "body": "Expose HPX build option which is fundamental to fully exploit all resources available on platforms with more than 64 cores.\r\n\r\n@msimberg can you check if it is ok for you or something is missing, please?",
    "performed_via_github_app": null
}