{
    "url": "https://api.github.com/repos/spack/spack/issues/17947",
    "repository_url": "https://api.github.com/repos/spack/spack",
    "labels_url": "https://api.github.com/repos/spack/spack/issues/17947/labels{/name}",
    "comments_url": "https://api.github.com/repos/spack/spack/issues/17947/comments",
    "events_url": "https://api.github.com/repos/spack/spack/issues/17947/events",
    "html_url": "https://github.com/spack/spack/issues/17947",
    "id": 675406532,
    "node_id": "MDU6SXNzdWU2NzU0MDY1MzI=",
    "number": 17947,
    "title": "Installation issue: ace",
    "user": {
        "login": "darmac",
        "id": 29532367,
        "node_id": "MDQ6VXNlcjI5NTMyMzY3",
        "avatar_url": "https://avatars.githubusercontent.com/u/29532367?v=4",
        "gravatar_id": "",
        "url": "https://api.github.com/users/darmac",
        "html_url": "https://github.com/darmac",
        "followers_url": "https://api.github.com/users/darmac/followers",
        "following_url": "https://api.github.com/users/darmac/following{/other_user}",
        "gists_url": "https://api.github.com/users/darmac/gists{/gist_id}",
        "starred_url": "https://api.github.com/users/darmac/starred{/owner}{/repo}",
        "subscriptions_url": "https://api.github.com/users/darmac/subscriptions",
        "organizations_url": "https://api.github.com/users/darmac/orgs",
        "repos_url": "https://api.github.com/users/darmac/repos",
        "events_url": "https://api.github.com/users/darmac/events{/privacy}",
        "received_events_url": "https://api.github.com/users/darmac/received_events",
        "type": "User",
        "site_admin": false
    },
    "labels": [
        {
            "id": 446616547,
            "node_id": "MDU6TGFiZWw0NDY2MTY1NDc=",
            "url": "https://api.github.com/repos/spack/spack/labels/build-error",
            "name": "build-error",
            "color": "ff3300",
            "default": false,
            "description": null
        },
        {
            "id": 921357381,
            "node_id": "MDU6TGFiZWw5MjEzNTczODE=",
            "url": "https://api.github.com/repos/spack/spack/labels/checksum",
            "name": "checksum",
            "color": "54d8b5",
            "default": false,
            "description": "Tarball checksum mismatches."
        },
        {
            "id": 446643530,
            "node_id": "MDU6TGFiZWw0NDY2NDM1MzA=",
            "url": "https://api.github.com/repos/spack/spack/labels/fetching",
            "name": "fetching",
            "color": "fbca04",
            "default": false,
            "description": null
        }
    ],
    "state": "open",
    "locked": false,
    "assignee": null,
    "assignees": [],
    "milestone": null,
    "comments": 3,
    "created_at": "2020-08-08T02:31:54Z",
    "updated_at": "2021-01-18T01:05:36Z",
    "closed_at": null,
    "author_association": "CONTRIBUTOR",
    "active_lock_reason": null,
    "body": "`ace` stage error(I'm not sure it's my internet problem or not), after I change the hash, `ace` can install successfully:\r\n```\r\n==> Installing ace\r\n==> No binary for ace found: installing from source\r\n==> Error: ChecksumError: sha256 checksum failed for /tmp/root/spack-stage/spack-stage-ace-6.5.6-kjxukcyj2xjqtjcugfati6oig6ldhlks/ACE-6.5.6.tar.gz\r\n    Expected 7717cad84d4a9c3d6b2c47963eb555d96de0be657870bcab6fcef4c0423af0de but got b6f9ec922fbdcecb4348e16d851d0d1f135df1836dfe77d2e0b64295ddb83066\r\n\r\n/home/xiaojun/spack/lib/spack/spack/package.py:1153, in do_fetch:\r\n       1150        self.stage.fetch(mirror_only)\r\n       1151        self._fetch_time = time.time() - start_time\r\n       1152\r\n  >>   1153        if checksum and self.version in self.versions:\r\n       1154            self.stage.check()\r\n       1155\r\n       1156        self.stage.cache_local()\r\n```",
    "performed_via_github_app": null
}