{
    "url": "https://api.github.com/repos/spack/spack/issues/18754",
    "repository_url": "https://api.github.com/repos/spack/spack",
    "labels_url": "https://api.github.com/repos/spack/spack/issues/18754/labels{/name}",
    "comments_url": "https://api.github.com/repos/spack/spack/issues/18754/comments",
    "events_url": "https://api.github.com/repos/spack/spack/issues/18754/events",
    "html_url": "https://github.com/spack/spack/pull/18754",
    "id": 704732570,
    "node_id": "MDExOlB1bGxSZXF1ZXN0NDg5NjAxNTQy",
    "number": 18754,
    "title": "workaround to ILCSoft/LCIO#114 parallel builds",
    "user": {
        "login": "joequant",
        "id": 2908185,
        "node_id": "MDQ6VXNlcjI5MDgxODU=",
        "avatar_url": "https://avatars.githubusercontent.com/u/2908185?v=4",
        "gravatar_id": "",
        "url": "https://api.github.com/users/joequant",
        "html_url": "https://github.com/joequant",
        "followers_url": "https://api.github.com/users/joequant/followers",
        "following_url": "https://api.github.com/users/joequant/following{/other_user}",
        "gists_url": "https://api.github.com/users/joequant/gists{/gist_id}",
        "starred_url": "https://api.github.com/users/joequant/starred{/owner}{/repo}",
        "subscriptions_url": "https://api.github.com/users/joequant/subscriptions",
        "organizations_url": "https://api.github.com/users/joequant/orgs",
        "repos_url": "https://api.github.com/users/joequant/repos",
        "events_url": "https://api.github.com/users/joequant/events{/privacy}",
        "received_events_url": "https://api.github.com/users/joequant/received_events",
        "type": "User",
        "site_admin": false
    },
    "labels": [
        {
            "id": 620268714,
            "node_id": "MDU6TGFiZWw2MjAyNjg3MTQ=",
            "url": "https://api.github.com/repos/spack/spack/labels/patch",
            "name": "patch",
            "color": "5319e7",
            "default": false,
            "description": null
        }
    ],
    "state": "closed",
    "locked": false,
    "assignee": null,
    "assignees": [],
    "milestone": null,
    "comments": 5,
    "created_at": "2020-09-19T01:20:39Z",
    "updated_at": "2020-10-11T05:12:07Z",
    "closed_at": "2020-10-11T02:15:04Z",
    "author_association": "CONTRIBUTOR",
    "active_lock_reason": null,
    "pull_request": {
        "url": "https://api.github.com/repos/spack/spack/pulls/18754",
        "html_url": "https://github.com/spack/spack/pull/18754",
        "diff_url": "https://github.com/spack/spack/pull/18754.diff",
        "patch_url": "https://github.com/spack/spack/pull/18754.patch"
    },
    "body": "This is a workaround for a missing dependency for Lcio\r\nthat shows up in massive builds",
    "performed_via_github_app": null
}