{
    "url": "https://api.github.com/repos/spack/spack/issues/21718",
    "repository_url": "https://api.github.com/repos/spack/spack",
    "labels_url": "https://api.github.com/repos/spack/spack/issues/21718/labels{/name}",
    "comments_url": "https://api.github.com/repos/spack/spack/issues/21718/comments",
    "events_url": "https://api.github.com/repos/spack/spack/issues/21718/events",
    "html_url": "https://github.com/spack/spack/pull/21718",
    "id": 809878901,
    "node_id": "MDExOlB1bGxSZXF1ZXN0NTc0NjYzOTQx",
    "number": 21718,
    "title": "dlib: added imgcodecs",
    "user": {
        "login": "h-denpo",
        "id": 57649496,
        "node_id": "MDQ6VXNlcjU3NjQ5NDk2",
        "avatar_url": "https://avatars.githubusercontent.com/u/57649496?v=4",
        "gravatar_id": "",
        "url": "https://api.github.com/users/h-denpo",
        "html_url": "https://github.com/h-denpo",
        "followers_url": "https://api.github.com/users/h-denpo/followers",
        "following_url": "https://api.github.com/users/h-denpo/following{/other_user}",
        "gists_url": "https://api.github.com/users/h-denpo/gists{/gist_id}",
        "starred_url": "https://api.github.com/users/h-denpo/starred{/owner}{/repo}",
        "subscriptions_url": "https://api.github.com/users/h-denpo/subscriptions",
        "organizations_url": "https://api.github.com/users/h-denpo/orgs",
        "repos_url": "https://api.github.com/users/h-denpo/repos",
        "events_url": "https://api.github.com/users/h-denpo/events{/privacy}",
        "received_events_url": "https://api.github.com/users/h-denpo/received_events",
        "type": "User",
        "site_admin": false
    },
    "labels": [],
    "state": "closed",
    "locked": false,
    "assignee": null,
    "assignees": [],
    "milestone": null,
    "comments": 0,
    "created_at": "2021-02-17T05:53:38Z",
    "updated_at": "2021-03-09T07:42:52Z",
    "closed_at": "2021-02-18T10:02:24Z",
    "author_association": "CONTRIBUTOR",
    "active_lock_reason": null,
    "pull_request": {
        "url": "https://api.github.com/repos/spack/spack/pulls/21718",
        "html_url": "https://github.com/spack/spack/pull/21718",
        "diff_url": "https://github.com/spack/spack/pull/21718.diff",
        "patch_url": "https://github.com/spack/spack/pull/21718.patch"
    },
    "body": "Since a variant (imgcodecs,default=False) has been added to opencv,\r\n+imgcodecs is now required in dlib's opencv dependency.\r\n\r\n```\r\n  >> 69    /tmp/denpo/spack-stage/spack-stage-dlib-master-aohosnmtozxzidqcxwatj4gse2lfgzsw/spack-src/src/DVision/Mat[29/1911]\r\n           :15:10: fatal error: opencv2/highgui/highgui.hpp: No such file or directory\r\n     70     #include <opencv2/highgui/highgui.hpp>\r\n     71              ^~~~~~~~~~~~~~~~~~~~~~~~~~~~~\r\n     72    compilation terminated.\r\n  >> 73    /tmp/denpo/spack-stage/spack-stage-dlib-master-aohosnmtozxzidqcxwatj4gse2lfgzsw/spack-src/src/DUtilsCV/Drawing.cp\r\n           p:13:10: fatal error: opencv2/highgui/highgui.hpp: No such file or directory\r\n     74     #include <opencv2/highgui/highgui.hpp>\r\n     75              ^~~~~~~~~~~~~~~~~~~~~~~~~~~~~\r\n     76    compilation terminated.\r\n  >> 77    make[2]: *** [CMakeFiles/DLib.dir/build.make:163: CMakeFiles/DLib.dir/src/DVision/Matches.cpp.o] Error 1\r\n     78    make[2]: *** Waiting for unfinished jobs....\r\n  >> 79    make[2]: *** [CMakeFiles/DLib.dir/build.make:202: CMakeFiles/DLib.dir/src/DUtilsCV/Drawing.cpp.o] Error 1\r\n  >> 80    /tmp/denpo/spack-stage/spack-stage-dlib-master-aohosnmtozxzidqcxwatj4gse2lfgzsw/spack-src/src/DUtilsCV/IO.cpp:14:\r\n           10: fatal error: opencv2/highgui/highgui.hpp: No such file or directory\r\n     81     #include <opencv2/highgui/highgui.hpp>\r\n     82              ^~~~~~~~~~~~~~~~~~~~~~~~~~~~~\r\n     83    compilation terminated.\r\n  >> 84    make[2]: *** [CMakeFiles/DLib.dir/build.make:267: CMakeFiles/DLib.dir/src/DUtilsCV/IO.cpp.o] Error 1\r\n  >> 85    /tmp/denpo/spack-stage/spack-stage-dlib-master-aohosnmtozxzidqcxwatj4gse2lfgzsw/spack-src/src/DUtilsCV/GUI.cpp:14\r\n           :10: fatal error: opencv2/highgui/highgui.hpp: No such file or directory\r\n     86     #include <opencv2/highgui/highgui.hpp>\r\n```\r\n",
    "performed_via_github_app": null
}