{
    "url": "https://api.github.com/repos/spack/spack/issues/23725",
    "repository_url": "https://api.github.com/repos/spack/spack",
    "labels_url": "https://api.github.com/repos/spack/spack/issues/23725/labels{/name}",
    "comments_url": "https://api.github.com/repos/spack/spack/issues/23725/comments",
    "events_url": "https://api.github.com/repos/spack/spack/issues/23725/events",
    "html_url": "https://github.com/spack/spack/pull/23725",
    "id": 894128693,
    "node_id": "MDExOlB1bGxSZXF1ZXN0NjQ2NTM5MjIw",
    "number": 23725,
    "title": "py-setuptools: add older version 41.3.0",
    "user": {
        "login": "healther",
        "id": 4048699,
        "node_id": "MDQ6VXNlcjQwNDg2OTk=",
        "avatar_url": "https://avatars.githubusercontent.com/u/4048699?v=4",
        "gravatar_id": "",
        "url": "https://api.github.com/users/healther",
        "html_url": "https://github.com/healther",
        "followers_url": "https://api.github.com/users/healther/followers",
        "following_url": "https://api.github.com/users/healther/following{/other_user}",
        "gists_url": "https://api.github.com/users/healther/gists{/gist_id}",
        "starred_url": "https://api.github.com/users/healther/starred{/owner}{/repo}",
        "subscriptions_url": "https://api.github.com/users/healther/subscriptions",
        "organizations_url": "https://api.github.com/users/healther/orgs",
        "repos_url": "https://api.github.com/users/healther/repos",
        "events_url": "https://api.github.com/users/healther/events{/privacy}",
        "received_events_url": "https://api.github.com/users/healther/received_events",
        "type": "User",
        "site_admin": false
    },
    "labels": [
        {
            "id": 446616788,
            "node_id": "MDU6TGFiZWw0NDY2MTY3ODg=",
            "url": "https://api.github.com/repos/spack/spack/labels/new-version",
            "name": "new-version",
            "color": "0e8a16",
            "default": false,
            "description": null
        }
    ],
    "state": "closed",
    "locked": false,
    "assignee": null,
    "assignees": [],
    "milestone": null,
    "comments": 2,
    "created_at": "2021-05-18T08:38:52Z",
    "updated_at": "2021-05-20T07:03:36Z",
    "closed_at": "2021-05-19T20:06:44Z",
    "author_association": "CONTRIBUTOR",
    "active_lock_reason": null,
    "pull_request": {
        "url": "https://api.github.com/repos/spack/spack/pulls/23725",
        "html_url": "https://github.com/spack/spack/pull/23725",
        "diff_url": "https://github.com/spack/spack/pull/23725.diff",
        "patch_url": "https://github.com/spack/spack/pull/23725.patch"
    },
    "body": "Part of our recent merge and upstream effort.",
    "performed_via_github_app": null
}