{
    "url": "https://api.github.com/repos/spack/spack/issues/24467",
    "repository_url": "https://api.github.com/repos/spack/spack",
    "labels_url": "https://api.github.com/repos/spack/spack/issues/24467/labels{/name}",
    "comments_url": "https://api.github.com/repos/spack/spack/issues/24467/comments",
    "events_url": "https://api.github.com/repos/spack/spack/issues/24467/events",
    "html_url": "https://github.com/spack/spack/pull/24467",
    "id": 927369014,
    "node_id": "MDExOlB1bGxSZXF1ZXN0Njc1NTM3MDAw",
    "number": 24467,
    "title": "genfit: Add googletest dependency",
    "user": {
        "login": "tmadlener",
        "id": 16774861,
        "node_id": "MDQ6VXNlcjE2Nzc0ODYx",
        "avatar_url": "https://avatars.githubusercontent.com/u/16774861?v=4",
        "gravatar_id": "",
        "url": "https://api.github.com/users/tmadlener",
        "html_url": "https://github.com/tmadlener",
        "followers_url": "https://api.github.com/users/tmadlener/followers",
        "following_url": "https://api.github.com/users/tmadlener/following{/other_user}",
        "gists_url": "https://api.github.com/users/tmadlener/gists{/gist_id}",
        "starred_url": "https://api.github.com/users/tmadlener/starred{/owner}{/repo}",
        "subscriptions_url": "https://api.github.com/users/tmadlener/subscriptions",
        "organizations_url": "https://api.github.com/users/tmadlener/orgs",
        "repos_url": "https://api.github.com/users/tmadlener/repos",
        "events_url": "https://api.github.com/users/tmadlener/events{/privacy}",
        "received_events_url": "https://api.github.com/users/tmadlener/received_events",
        "type": "User",
        "site_admin": false
    },
    "labels": [],
    "state": "closed",
    "locked": false,
    "assignee": {
        "login": "scheibelp",
        "id": 1659704,
        "node_id": "MDQ6VXNlcjE2NTk3MDQ=",
        "avatar_url": "https://avatars.githubusercontent.com/u/1659704?v=4",
        "gravatar_id": "",
        "url": "https://api.github.com/users/scheibelp",
        "html_url": "https://github.com/scheibelp",
        "followers_url": "https://api.github.com/users/scheibelp/followers",
        "following_url": "https://api.github.com/users/scheibelp/following{/other_user}",
        "gists_url": "https://api.github.com/users/scheibelp/gists{/gist_id}",
        "starred_url": "https://api.github.com/users/scheibelp/starred{/owner}{/repo}",
        "subscriptions_url": "https://api.github.com/users/scheibelp/subscriptions",
        "organizations_url": "https://api.github.com/users/scheibelp/orgs",
        "repos_url": "https://api.github.com/users/scheibelp/repos",
        "events_url": "https://api.github.com/users/scheibelp/events{/privacy}",
        "received_events_url": "https://api.github.com/users/scheibelp/received_events",
        "type": "User",
        "site_admin": false
    },
    "assignees": [
        {
            "login": "scheibelp",
            "id": 1659704,
            "node_id": "MDQ6VXNlcjE2NTk3MDQ=",
            "avatar_url": "https://avatars.githubusercontent.com/u/1659704?v=4",
            "gravatar_id": "",
            "url": "https://api.github.com/users/scheibelp",
            "html_url": "https://github.com/scheibelp",
            "followers_url": "https://api.github.com/users/scheibelp/followers",
            "following_url": "https://api.github.com/users/scheibelp/following{/other_user}",
            "gists_url": "https://api.github.com/users/scheibelp/gists{/gist_id}",
            "starred_url": "https://api.github.com/users/scheibelp/starred{/owner}{/repo}",
            "subscriptions_url": "https://api.github.com/users/scheibelp/subscriptions",
            "organizations_url": "https://api.github.com/users/scheibelp/orgs",
            "repos_url": "https://api.github.com/users/scheibelp/repos",
            "events_url": "https://api.github.com/users/scheibelp/events{/privacy}",
            "received_events_url": "https://api.github.com/users/scheibelp/received_events",
            "type": "User",
            "site_admin": false
        }
    ],
    "milestone": null,
    "comments": 1,
    "created_at": "2021-06-22T15:34:39Z",
    "updated_at": "2021-06-30T05:37:35Z",
    "closed_at": "2021-06-30T05:37:25Z",
    "author_association": "CONTRIBUTOR",
    "active_lock_reason": null,
    "pull_request": {
        "url": "https://api.github.com/repos/spack/spack/pulls/24467",
        "html_url": "https://github.com/spack/spack/pull/24467",
        "diff_url": "https://github.com/spack/spack/pull/24467.diff",
        "patch_url": "https://github.com/spack/spack/pull/24467.patch"
    },
    "body": "Not strictly necessary, but building the tests implicitly depends on the presence of `gtest`. To avoid that a potentially incompatible version provided by the system interferes, make sure that a version that is compiled with the same compiler as `genfit` is available.",
    "performed_via_github_app": null
}