{
    "url": "https://api.github.com/repos/spack/spack/issues/3363",
    "repository_url": "https://api.github.com/repos/spack/spack",
    "labels_url": "https://api.github.com/repos/spack/spack/issues/3363/labels{/name}",
    "comments_url": "https://api.github.com/repos/spack/spack/issues/3363/comments",
    "events_url": "https://api.github.com/repos/spack/spack/issues/3363/events",
    "html_url": "https://github.com/spack/spack/pull/3363",
    "id": 211848957,
    "node_id": "MDExOlB1bGxSZXF1ZXN0MTA5MDkwMDUx",
    "number": 3363,
    "title": "Allow find_libraries to accept lists or strings",
    "user": {
        "login": "adamjstewart",
        "id": 12021217,
        "node_id": "MDQ6VXNlcjEyMDIxMjE3",
        "avatar_url": "https://avatars.githubusercontent.com/u/12021217?v=4",
        "gravatar_id": "",
        "url": "https://api.github.com/users/adamjstewart",
        "html_url": "https://github.com/adamjstewart",
        "followers_url": "https://api.github.com/users/adamjstewart/followers",
        "following_url": "https://api.github.com/users/adamjstewart/following{/other_user}",
        "gists_url": "https://api.github.com/users/adamjstewart/gists{/gist_id}",
        "starred_url": "https://api.github.com/users/adamjstewart/starred{/owner}{/repo}",
        "subscriptions_url": "https://api.github.com/users/adamjstewart/subscriptions",
        "organizations_url": "https://api.github.com/users/adamjstewart/orgs",
        "repos_url": "https://api.github.com/users/adamjstewart/repos",
        "events_url": "https://api.github.com/users/adamjstewart/events{/privacy}",
        "received_events_url": "https://api.github.com/users/adamjstewart/received_events",
        "type": "User",
        "site_admin": false
    },
    "labels": [],
    "state": "closed",
    "locked": false,
    "assignee": null,
    "assignees": [],
    "milestone": null,
    "comments": 9,
    "created_at": "2017-03-04T02:45:23Z",
    "updated_at": "2017-03-04T23:40:29Z",
    "closed_at": "2017-03-04T17:23:58Z",
    "author_association": "MEMBER",
    "active_lock_reason": null,
    "pull_request": {
        "url": "https://api.github.com/repos/spack/spack/pulls/3363",
        "html_url": "https://github.com/spack/spack/pull/3363",
        "diff_url": "https://github.com/spack/spack/pull/3363.diff",
        "patch_url": "https://github.com/spack/spack/pull/3363.patch"
    },
    "body": "",
    "performed_via_github_app": null
}