{
    "url": "https://api.github.com/repos/spack/spack/issues/4735",
    "repository_url": "https://api.github.com/repos/spack/spack",
    "labels_url": "https://api.github.com/repos/spack/spack/issues/4735/labels{/name}",
    "comments_url": "https://api.github.com/repos/spack/spack/issues/4735/comments",
    "events_url": "https://api.github.com/repos/spack/spack/issues/4735/events",
    "html_url": "https://github.com/spack/spack/pull/4735",
    "id": 242324147,
    "node_id": "MDExOlB1bGxSZXF1ZXN0MTMwMDk5NDg2",
    "number": 4735,
    "title": "dealii: workaround for concretization bug",
    "user": {
        "login": "davydden",
        "id": 8023934,
        "node_id": "MDQ6VXNlcjgwMjM5MzQ=",
        "avatar_url": "https://avatars.githubusercontent.com/u/8023934?v=4",
        "gravatar_id": "",
        "url": "https://api.github.com/users/davydden",
        "html_url": "https://github.com/davydden",
        "followers_url": "https://api.github.com/users/davydden/followers",
        "following_url": "https://api.github.com/users/davydden/following{/other_user}",
        "gists_url": "https://api.github.com/users/davydden/gists{/gist_id}",
        "starred_url": "https://api.github.com/users/davydden/starred{/owner}{/repo}",
        "subscriptions_url": "https://api.github.com/users/davydden/subscriptions",
        "organizations_url": "https://api.github.com/users/davydden/orgs",
        "repos_url": "https://api.github.com/users/davydden/repos",
        "events_url": "https://api.github.com/users/davydden/events{/privacy}",
        "received_events_url": "https://api.github.com/users/davydden/received_events",
        "type": "User",
        "site_admin": false
    },
    "labels": [
        {
            "id": 73908754,
            "node_id": "MDU6TGFiZWw3MzkwODc1NA==",
            "url": "https://api.github.com/repos/spack/spack/labels/bug",
            "name": "bug",
            "color": "fc2929",
            "default": true,
            "description": null
        },
        {
            "id": 446623646,
            "node_id": "MDU6TGFiZWw0NDY2MjM2NDY=",
            "url": "https://api.github.com/repos/spack/spack/labels/concretization",
            "name": "concretization",
            "color": "006b75",
            "default": false,
            "description": null
        }
    ],
    "state": "closed",
    "locked": false,
    "assignee": null,
    "assignees": [],
    "milestone": null,
    "comments": 0,
    "created_at": "2017-07-12T09:59:02Z",
    "updated_at": "2017-12-19T12:05:21Z",
    "closed_at": "2017-07-13T12:51:45Z",
    "author_association": "MEMBER",
    "active_lock_reason": null,
    "pull_request": {
        "url": "https://api.github.com/repos/spack/spack/pulls/4735",
        "html_url": "https://github.com/spack/spack/pull/4735",
        "diff_url": "https://github.com/spack/spack/pull/4735.diff",
        "patch_url": "https://github.com/spack/spack/pull/4735.patch"
    },
    "body": "also add `anasazi` to `trilinos`, which was removed recently when all the variants for its packages were introduced.",
    "performed_via_github_app": null
}