{
    "url": "https://api.github.com/repos/spack/spack/issues/5251",
    "repository_url": "https://api.github.com/repos/spack/spack",
    "labels_url": "https://api.github.com/repos/spack/spack/issues/5251/labels{/name}",
    "comments_url": "https://api.github.com/repos/spack/spack/issues/5251/comments",
    "events_url": "https://api.github.com/repos/spack/spack/issues/5251/events",
    "html_url": "https://github.com/spack/spack/pull/5251",
    "id": 254118526,
    "node_id": "MDExOlB1bGxSZXF1ZXN0MTM4NTE1NDA1",
    "number": 5251,
    "title": "Jags: Adding spec",
    "user": {
        "login": "zenln",
        "id": 1799907,
        "node_id": "MDQ6VXNlcjE3OTk5MDc=",
        "avatar_url": "https://avatars.githubusercontent.com/u/1799907?v=4",
        "gravatar_id": "",
        "url": "https://api.github.com/users/zenln",
        "html_url": "https://github.com/zenln",
        "followers_url": "https://api.github.com/users/zenln/followers",
        "following_url": "https://api.github.com/users/zenln/following{/other_user}",
        "gists_url": "https://api.github.com/users/zenln/gists{/gist_id}",
        "starred_url": "https://api.github.com/users/zenln/starred{/owner}{/repo}",
        "subscriptions_url": "https://api.github.com/users/zenln/subscriptions",
        "organizations_url": "https://api.github.com/users/zenln/orgs",
        "repos_url": "https://api.github.com/users/zenln/repos",
        "events_url": "https://api.github.com/users/zenln/events{/privacy}",
        "received_events_url": "https://api.github.com/users/zenln/received_events",
        "type": "User",
        "site_admin": false
    },
    "labels": [],
    "state": "closed",
    "locked": false,
    "assignee": null,
    "assignees": [],
    "milestone": null,
    "comments": 0,
    "created_at": "2017-08-30T20:03:07Z",
    "updated_at": "2017-08-31T13:53:45Z",
    "closed_at": "2017-08-31T13:53:45Z",
    "author_association": "CONTRIBUTOR",
    "active_lock_reason": null,
    "pull_request": {
        "url": "https://api.github.com/repos/spack/spack/pulls/5251",
        "html_url": "https://github.com/spack/spack/pull/5251",
        "diff_url": "https://github.com/spack/spack/pull/5251.diff",
        "patch_url": "https://github.com/spack/spack/pull/5251.patch"
    },
    "body": "Needs atlas.",
    "performed_via_github_app": null
}