{
    "url": "https://api.github.com/repos/spack/spack/issues/7426",
    "repository_url": "https://api.github.com/repos/spack/spack",
    "labels_url": "https://api.github.com/repos/spack/spack/issues/7426/labels{/name}",
    "comments_url": "https://api.github.com/repos/spack/spack/issues/7426/comments",
    "events_url": "https://api.github.com/repos/spack/spack/issues/7426/events",
    "html_url": "https://github.com/spack/spack/pull/7426",
    "id": 303531956,
    "node_id": "MDExOlB1bGxSZXF1ZXN0MTczNzc1MDA5",
    "number": 7426,
    "title": "py-python-levenshtein: Create new package",
    "user": {
        "login": "erimar77",
        "id": 6336162,
        "node_id": "MDQ6VXNlcjYzMzYxNjI=",
        "avatar_url": "https://avatars.githubusercontent.com/u/6336162?v=4",
        "gravatar_id": "",
        "url": "https://api.github.com/users/erimar77",
        "html_url": "https://github.com/erimar77",
        "followers_url": "https://api.github.com/users/erimar77/followers",
        "following_url": "https://api.github.com/users/erimar77/following{/other_user}",
        "gists_url": "https://api.github.com/users/erimar77/gists{/gist_id}",
        "starred_url": "https://api.github.com/users/erimar77/starred{/owner}{/repo}",
        "subscriptions_url": "https://api.github.com/users/erimar77/subscriptions",
        "organizations_url": "https://api.github.com/users/erimar77/orgs",
        "repos_url": "https://api.github.com/users/erimar77/repos",
        "events_url": "https://api.github.com/users/erimar77/events{/privacy}",
        "received_events_url": "https://api.github.com/users/erimar77/received_events",
        "type": "User",
        "site_admin": false
    },
    "labels": [
        {
            "id": 446619526,
            "node_id": "MDU6TGFiZWw0NDY2MTk1MjY=",
            "url": "https://api.github.com/repos/spack/spack/labels/new-package",
            "name": "new-package",
            "color": "444444",
            "default": false,
            "description": null
        }
    ],
    "state": "closed",
    "locked": false,
    "assignee": null,
    "assignees": [],
    "milestone": null,
    "comments": 2,
    "created_at": "2018-03-08T15:58:21Z",
    "updated_at": "2018-04-12T18:34:09Z",
    "closed_at": "2018-03-21T21:54:51Z",
    "author_association": "CONTRIBUTOR",
    "active_lock_reason": null,
    "pull_request": {
        "url": "https://api.github.com/repos/spack/spack/pulls/7426",
        "html_url": "https://github.com/spack/spack/pull/7426",
        "diff_url": "https://github.com/spack/spack/pull/7426.diff",
        "patch_url": "https://github.com/spack/spack/pull/7426.patch"
    },
    "body": "",
    "performed_via_github_app": null
}