{
    "url": "https://api.github.com/repos/spack/spack/issues/790",
    "repository_url": "https://api.github.com/repos/spack/spack",
    "labels_url": "https://api.github.com/repos/spack/spack/issues/790/labels{/name}",
    "comments_url": "https://api.github.com/repos/spack/spack/issues/790/comments",
    "events_url": "https://api.github.com/repos/spack/spack/issues/790/events",
    "html_url": "https://github.com/spack/spack/pull/790",
    "id": 148996992,
    "node_id": "MDExOlB1bGxSZXF1ZXN0NjY3ODEzMTk=",
    "number": 790,
    "title": "Update Package : Swig",
    "user": {
        "login": "xjrc",
        "id": 17277866,
        "node_id": "MDQ6VXNlcjE3Mjc3ODY2",
        "avatar_url": "https://avatars.githubusercontent.com/u/17277866?v=4",
        "gravatar_id": "",
        "url": "https://api.github.com/users/xjrc",
        "html_url": "https://github.com/xjrc",
        "followers_url": "https://api.github.com/users/xjrc/followers",
        "following_url": "https://api.github.com/users/xjrc/following{/other_user}",
        "gists_url": "https://api.github.com/users/xjrc/gists{/gist_id}",
        "starred_url": "https://api.github.com/users/xjrc/starred{/owner}{/repo}",
        "subscriptions_url": "https://api.github.com/users/xjrc/subscriptions",
        "organizations_url": "https://api.github.com/users/xjrc/orgs",
        "repos_url": "https://api.github.com/users/xjrc/repos",
        "events_url": "https://api.github.com/users/xjrc/events{/privacy}",
        "received_events_url": "https://api.github.com/users/xjrc/received_events",
        "type": "User",
        "site_admin": false
    },
    "labels": [],
    "state": "closed",
    "locked": false,
    "assignee": null,
    "assignees": [],
    "milestone": null,
    "comments": 1,
    "created_at": "2016-04-17T21:03:20Z",
    "updated_at": "2016-04-23T19:15:14Z",
    "closed_at": "2016-04-23T19:15:14Z",
    "author_association": "MEMBER",
    "active_lock_reason": null,
    "pull_request": {
        "url": "https://api.github.com/repos/spack/spack/pulls/790",
        "html_url": "https://github.com/spack/spack/pull/790",
        "diff_url": "https://github.com/spack/spack/pull/790.diff",
        "patch_url": "https://github.com/spack/spack/pull/790.patch"
    },
    "body": "The changes in this pull request simply augment the Swig package file by adding installation support for a number of the most popular Swig versions.  I've verified that all of these new versions build properly on the CHAOS platform when compiling with gcc@4.7.2.\n",
    "performed_via_github_app": null
}